BasicModules.v
// Full Adder
module full_adder(input wire a, b, c_in, output wire s, c_out);
	assign s = a ^ b ^ c_in;
    assign c_out = a&b | b&c_in | a&c_in;
endmodule

// Half Adder
module half_adder(input wire a, b, output wire s, c_out);
	assign s = a ^ b;
    assign c_out = a&b;
endmodule

// 2:1 MUX
module mux_2_1(input wire i0, i1, j, output wire o);
	assign o = i0&(~j) | i1&j;
endmodule

// 1:2 DEMUX
module demux_1_2(input wire i, j, output wire o0, o1);
	assign o0 = i&(~j);
    assign o1 = i&j;
endmodule

// 1:2 DECODER
module decoder_1_2(input wire j, output wire o0, o1);
	assign o0 = ~j;
    assign o1 = j;
endmodule

// SR Latch
module sr_latch(input wire s, r, output wire q, not_q);
	assign q = ~(r | not_q);
    assign not_q = ~(s | q);
endmodule

// D Flip Flop
module d_flip_flop(input wire d, clk, output wire q, not_q);
	wire r,s;
    assign r = clk & (~d);
    assign s = clk & d;
    sr_latch sr_1(s, r, q, not_q);
endmodule

testbench.v
`timescale 1 ns / 100 ps
`define TESTVECS 8

module tb;
  reg clk, reset;
  reg d;
  wire q, not_q;
  reg test_vecs [0:(`TESTVECS-1)];
  integer i;
  initial begin $dumpfile("BasicModules.vcd"); $dumpvars(0,tb); end
  initial begin reset = 1'b1; #12.5 reset = 1'b0; end
  initial clk = 1'b0; always #5 clk =~ clk;
  initial begin
  	//test_vecs[0][33:32] = 2'b00; test_vecs[0][31:8] = 16'h00;test_vecs[0][15:0] = 16'h00;
    
    test_vecs[0] = 1'b0;
    test_vecs[1] = 1'b0;
    test_vecs[2] = 1'b1;
    test_vecs[3] = 1'b1;
    test_vecs[4] = 1'b1;
    test_vecs[5] = 1'b0;
    test_vecs[6] = 1'b1;
    test_vecs[7] = 1'b0;
    
  end
  initial {d} = 0;
  d_flip_flop dfl_0 (d, clk, q, not_q);
  initial begin
    #6 for(i=0;i<`TESTVECS;i=i+1)
      begin #10 d=test_vecs[i]; end
    #100 $finish;
  end
endmodule

BasicModules.vcd
$date
	Tue Jan 12 18:14:16 2021
$end
$version
	Icarus Verilog
$end
$timescale
	100ps
$end
$scope module tb $end
$var wire 1 ! q $end
$var wire 1 " not_q $end
$var reg 1 # clk $end
$var reg 1 $ d $end
$var reg 1 % reset $end
$var integer 32 & i [31:0] $end
$scope module dfl_0 $end
$var wire 1 # clk $end
$var wire 1 $ d $end
$var wire 1 ' r $end
$var wire 1 ( s $end
$var wire 1 ! q $end
$var wire 1 " not_q $end
$scope module sr_1 $end
$var wire 1 " not_q $end
$var wire 1 ! q $end
$var wire 1 ' r $end
$var wire 1 ( s $end
$upscope $end
$upscope $end
$upscope $end
$enddefinitions $end
#0
$dumpvars
0(
0'
bx &
1%
0$
0#
x"
x!
$end
#50
1"
0!
1'
1#
#60
b0 &
#100
0'
0#
#125
0%
#150
1'
1#
#160
b1 &
#200
0'
0#
#250
1'
1#
#260
b10 &
#300
0'
0#
#350
1'
1#
#360
1!
0"
0'
1(
b11 &
1$
#400
0(
0#
#450
1(
1#
#460
b100 &
#500
0(
0#
#550
1(
1#
#560
b101 &
#600
0(
0#
#650
1(
1#
#660
1"
0!
1'
0(
b110 &
0$
#700
0'
0#
#750
1'
1#
#760
1!
0"
0'
1(
b111 &
1$
#800
0(
0#
#850
1(
1#
#860
1"
0!
1'
0(
b1000 &
0$
#900
0'
0#
#950
1'
1#
#1000
0'
0#
#1050
1'
1#
#1100
0'
0#
#1150
1'
1#
#1200
0'
0#
#1250
1'
1#
#1300
0'
0#
#1350
1'
1#
#1400
0'
0#
#1450
1'
1#
#1500
0'
0#
#1550
1'
1#
#1600
0'
0#
#1650
1'
1#
#1700
0'
0#
#1750
1'
1#
#1800
0'
0#
#1850
1'
1#
