latch.v
// SR Latch
module sr_latch(input wire s, r, output wire q, not_q);
	assign q = ~(r | not_q);
    assign not_q = ~(s | q);
endmodule

// D latch
module d_latch(input wire d, clk, output wire q, not_q);
	wire r,s;
    assign r = clk & (~d);
    assign s = clk & d;
    sr_latch sr_1(s, r, q, not_q);
endmodule

flip_flop.v
`include "latch.v"
// D Flip Flop
module d_flip_flop(input wire d, clk, output wire q, not_q);
	wire t, not_t;
    d_latch dl1(d, ~clk, t, not_t);
    d_latch dl2(t, clk, q, not_q);
endmodule

testbench.v
`include "flip_flop.v"
`timescale 1 ns / 100 ps
`define TESTVECS 8

module tb;
  reg clk, reset;
  reg d;
  wire q, not_q;
  reg test_vecs [0:(`TESTVECS-1)];
  integer i;
  initial begin $dumpfile("BasicModules.vcd"); $dumpvars(0,tb); end
  initial begin reset = 1'b1; #12.5 reset = 1'b0; end
  initial clk = 1'b0; always #5 clk =~ clk;
  initial begin
  	//test_vecs[0][33:32] = 2'b00; test_vecs[0][31:8] = 16'h00;test_vecs[0][15:0] = 16'h00;
    
    test_vecs[0] = 1'b0;
    test_vecs[1] = 1'b0;
    test_vecs[2] = 1'b1;
    test_vecs[3] = 1'b1;
    test_vecs[4] = 1'b1;
    test_vecs[5] = 1'b0;
    test_vecs[6] = 1'b1;
    test_vecs[7] = 1'b0;
    
  end
  initial {d} = 0;
  d_flip_flop dfl_0 (d, clk, q, not_q);
  initial begin
    #6 for(i=0;i<`TESTVECS;i=i+1)
      begin #10 d=test_vecs[i]; end
    #100 $finish;
  end
endmodule

BasicModules.vcd
$date
	Fri Jan 15 17:49:07 2021
$end
$version
	Icarus Verilog
$end
$timescale
	100ps
$end
$scope module tb $end
$var wire 1 ! q $end
$var wire 1 " not_q $end
$var reg 1 # clk $end
$var reg 1 $ d $end
$var reg 1 % reset $end
$var integer 32 & i [31:0] $end
$scope module dfl_0 $end
$var wire 1 # clk $end
$var wire 1 $ d $end
$var wire 1 ' t $end
$var wire 1 ! q $end
$var wire 1 ( not_t $end
$var wire 1 " not_q $end
$scope module dl1 $end
$var wire 1 ) clk $end
$var wire 1 $ d $end
$var wire 1 * r $end
$var wire 1 + s $end
$var wire 1 ' q $end
$var wire 1 ( not_q $end
$scope module sr_1 $end
$var wire 1 ( not_q $end
$var wire 1 ' q $end
$var wire 1 * r $end
$var wire 1 + s $end
$upscope $end
$upscope $end
$scope module dl2 $end
$var wire 1 # clk $end
$var wire 1 ' d $end
$var wire 1 , r $end
$var wire 1 - s $end
$var wire 1 ! q $end
$var wire 1 " not_q $end
$scope module sr_1 $end
$var wire 1 " not_q $end
$var wire 1 ! q $end
$var wire 1 , r $end
$var wire 1 - s $end
$upscope $end
$upscope $end
$upscope $end
$upscope $end
$enddefinitions $end
#0
$dumpvars
0-
0,
0+
1*
1)
1(
0'
bx &
1%
0$
0#
x"
x!
$end
#50
1"
0!
0*
0)
1,
1#
#60
b0 &
#100
1*
1)
0,
0#
#125
0%
#150
0*
0)
1,
1#
#160
b1 &
#200
1*
1)
0,
0#
#250
0*
0)
1,
1#
#260
b10 &
#300
1*
1)
0,
0#
#350
0*
0)
1,
1#
#360
b11 &
1$
#400
1'
0(
1+
1)
0,
0#
#450
1!
0"
0+
0)
1-
1#
#460
b100 &
#500
1+
1)
0-
0#
#550
0+
0)
1-
1#
#560
b101 &
#600
1+
1)
0-
0#
#650
0+
0)
1-
1#
#660
b110 &
0$
#700
1(
0'
1*
1)
0-
0#
#750
1"
0!
0*
0)
1,
1#
#760
b111 &
1$
#800
1'
0(
1+
1)
0,
0#
#850
1!
0"
0+
0)
1-
1#
#860
b1000 &
0$
#900
1(
0'
1*
1)
0-
0#
#950
1"
0!
0*
0)
1,
1#
#1000
1*
1)
0,
0#
#1050
0*
0)
1,
1#
#1100
1*
1)
0,
0#
#1150
0*
0)
1,
1#
#1200
1*
1)
0,
0#
#1250
0*
0)
1,
1#
#1300
1*
1)
0,
0#
#1350
0*
0)
1,
1#
#1400
1*
1)
0,
0#
#1450
0*
0)
1,
1#
#1500
1*
1)
0,
0#
#1550
0*
0)
1,
1#
#1600
1*
1)
0,
0#
#1650
0*
0)
1,
1#
#1700
1*
1)
0,
0#
#1750
0*
0)
1,
1#
#1800
1*
1)
0,
0#
#1850
0*
0)
1,
1#
